tests/__init__.py
text_purify/__init__.py
text_purify-1.0.0.dist-info/LICENSE
text_purify-1.0.0.dist-info/METADATA
text_purify-1.0.0.dist-info/WHEEL
text_purify-1.0.0.dist-info/top_level.txt
text_purify-1.0.0.dist-info/RECORD
