Metadata-Version: 2.1
Name: text_purify
Version: 1.0.0
Summary: Text purify
Author: Krzysztof Żyłka
Author-email: krzysztofzylka@yahoo.com
Classifier: Programming Language :: Python :: 3
Classifier: License :: OSI Approved :: MIT License
Classifier: Operating System :: OS Independent
License-File: LICENSE
